yt_dlp_gui/__init__.py
yt_dlp_gui/__main__.py
yt_dlp_gui/config.py
yt_dlp_gui/main.py
yt_dlp_gui/worker.py
yt_dlp_gui/resources/logo.jpg
yt_dlp_qt_gui-0.2.0.dist-info/licenses/LICENSE
yt_dlp_qt_gui-0.2.0.dist-info/METADATA
yt_dlp_qt_gui-0.2.0.dist-info/WHEEL
yt_dlp_qt_gui-0.2.0.dist-info/entry_points.txt
yt_dlp_qt_gui-0.2.0.dist-info/top_level.txt
yt_dlp_qt_gui-0.2.0.dist-info/RECORD
