Metadata-Version: 2.4
Name: yt-dlp-qt-gui
Version: 0.2.0
Summary: 现代化视频下载工具，基于 yt-dlp 和 PySide6
Author-email: curry tang <twn39@163.com>
Maintainer-email: curry tang <twn39@163.com>
License-Expression: GPL-3.0-or-later
Project-URL: Homepage, https://github.com/twn39/yt-dlp-qt-gui
Project-URL: Documentation, https://github.com/twn39/yt-dlp-qt-gui#readme
Project-URL: Repository, https://github.com/twn39/yt-dlp-qt-gui
Project-URL: Issues, https://github.com/twn39/yt-dlp-qt-gui/issues
Keywords: video,download,yt-dlp,gui,pyside6,qt
Classifier: Development Status :: 4 - Beta
Classifier: Environment :: X11 Applications :: Qt
Classifier: Intended Audience :: End Users/Desktop
Classifier: Operating System :: OS Independent
Classifier: Programming Language :: Python :: 3
Classifier: Programming Language :: Python :: 3.12
Classifier: Programming Language :: Python :: 3.13
Classifier: Topic :: Multimedia :: Video
Classifier: Topic :: Utilities
Requires-Python: >=3.11
License-File: LICENSE
Requires-Dist: pyside6>=6.10.1
Requires-Dist: qtawesome>=1.4.0
Requires-Dist: yt-dlp>=2025.12.8
Requires-Dist: click>=8.1.0
Provides-Extra: packaging
Requires-Dist: pyinstaller>=6.0.0; extra == "packaging"
Provides-Extra: test
Requires-Dist: pytest>=8.0.0; extra == "test"
Requires-Dist: pytest-qt>=4.4.0; extra == "test"
Requires-Dist: pytest-mock>=3.12.0; extra == "test"
Requires-Dist: pytest-cov>=7.0.0; extra == "test"
Dynamic: license-file
